{
    "info": {
        "video_id": "C002673",
        "clip_id": "008",
        "device": "C",
        "time": "N",
        "weather": "F",
        "is_scripted": "0"
    },
    "description": {
        "frame_id": "0330",
        "imageWidth": 1920,
        "imageHeight": 1080
    },
    "annotations": {
        "environment": [
            {
                "area_code": "2",
                "shape_type": "polygon",
                "points": [
                    [
                        394.3605545871045,
                        656.0965712781397
                    ],
                    [
                        405.1403421703335,
                        813.4132354932004
                    ],
                    [
                        405.1403421703335,
                        1154.2660079591656
                    ],
                    [
                        437.4797049200206,
                        1414.9181280801977
                    ],
                    [
                        465.1991587054667,
                        1556.811589921233
                    ],
                    [
                        345.08152563520036,
                        1566.0655113456482
                    ],
                    [
                        320.44201115924835,
                        1306.9557114620186
                    ],
                    [
                        312.74216288551327,
                        926.0026128235871
                    ]
                ]
            },
            {
                "area_code": "7",
                "shape_type": "polygon",
                "points": [
                    [
                        465.1991587054667,
                        1118.7926424989068
                    ],
                    [
                        471.3590373244547,
                        1112.6233615492965
                    ],
                    [
                        479.05888559818965,
                        1165.0622496209835
                    ],
                    [
                        499.0784911099007,
                        1333.1751554978623
                    ],
                    [
                        520.6380662763588,
                        1467.3570161518846
                    ],
                    [
                        509.8582786931298,
                        1473.526297101495
                    ],
                    [
                        489.83867318141864,
                        1337.80211621007
                    ],
                    [
                        468.27909801496065,
                        1155.8083281965683
                    ],
                    [
                        465.1991587054667,
                        1129.5888841607248
                    ]
                ]
            },
            {
                "area_code": "8",
                "shape_type": "polygon",
                "points": [
                    [
                        462.1192193959726,
                        1137.3004853477375
                    ],
                    [
                        483.6787945624307,
                        1320.8365935986417
                    ],
                    [
                        503.6984000741417,
                        1470.4416566266898
                    ],
                    [
                        452.87940146749054,
                        1492.0341399503254
                    ],
                    [
                        406.6803118250805,
                        1143.4697662973476
                    ]
                ]
            },
            {
                "area_code": "12",
                "shape_type": "polygon",
                "points": [
                    [
                        49.40735192377566,
                        1297.7017900376034
                    ],
                    [
                        67.8869877807397,
                        1296.159469800201
                    ],
                    [
                        72.50689674498072,
                        1357.852279296303
                    ],
                    [
                        54.02726088801667,
                        1357.852279296303
                    ]
                ]
            }
        ],
        "PM": [
            {
                "PM_code": "18",
                "shape_type": "bbox",
                "points": [
                    1371.0,
                    246.51768173472433,
                    36.206526893185085,
                    72.48231826527572
                ]
            }
        ]
    }
}