{
    "info": {
        "video_id": "S000598",
        "clip_id": "005",
        "device": "C",
        "time": "N",
        "weather": "F",
        "is_scripted": "0"
    },
    "description": {
        "frame_id": "0028",
        "imageWidth": 1920,
        "imageHeight": 1080
    },
    "annotations": {
        "environment": [
            {
                "area_code": "1",
                "shape_type": "polygon",
                "points": [
                    [
                        386.3324833409836,
                        4.0356727775689425
                    ],
                    [
                        281.58175743868054,
                        369.3676464960935
                    ],
                    [
                        204.55916486345768,
                        612.9222956417766
                    ],
                    [
                        139.8601871002705,
                        719.284769002866
                    ],
                    [
                        118.29386117920811,
                        626.7956617323534
                    ],
                    [
                        190.69509819991757,
                        483.437545463059
                    ],
                    [
                        295.4458241022207,
                        27.15794959519707
                    ]
                ]
            },
            {
                "area_code": "2",
                "shape_type": "polygon",
                "points": [
                    [
                        591.2125795910764,
                        1377.4989157446803
                    ],
                    [
                        424.843779628595,
                        927.3852603615192
                    ],
                    [
                        281.58175743868054,
                        440.2759620701531
                    ],
                    [
                        212.26142412097997,
                        634.5030873382295
                    ],
                    [
                        247.69181670558248,
                        836.4376382121819
                    ],
                    [
                        392.4942907470014,
                        1451.4902015610905
                    ]
                ]
            },
            {
                "area_code": "3",
                "shape_type": "polygon",
                "points": [
                    [
                        709.8273721569195,
                        1328.1713918670737
                    ],
                    [
                        580.4294166305451,
                        1405.2456479258342
                    ],
                    [
                        464.8955277677108,
                        1032.2062486014336
                    ],
                    [
                        272.3390463296538,
                        424.8611108584011
                    ],
                    [
                        307.7694389142563,
                        346.24536967846535
                    ],
                    [
                        427.9246833316039,
                        683.8306112158361
                    ],
                    [
                        575.8080610760317,
                        1032.2062486014336
                    ]
                ]
            },
            {
                "area_code": "4",
                "shape_type": "polygon",
                "points": [
                    [
                        391.72406482124916,
                        1456.1146569246162
                    ],
                    [
                        219.19345745275004,
                        1505.4421808022225
                    ],
                    [
                        146.79222043204055,
                        1305.0491150494456
                    ],
                    [
                        262.3261092948748,
                        911.9704091497671
                    ]
                ]
            },
            {
                "area_code": "7",
                "shape_type": "polygon",
                "points": [
                    [
                        954.7592165461281,
                        1234.1407994753858
                    ],
                    [
                        472.5977870252331,
                        454.1493281607301
                    ],
                    [
                        423.30332777709043,
                        381.69952746549524
                    ],
                    [
                        407.8988092620459,
                        414.07071501017464
                    ],
                    [
                        471.0573351737286,
                        518.8917032500889
                    ],
                    [
                        785.3095128806378,
                        1079.992287357865
                    ],
                    [
                        883.8984313769231,
                        1269.5949572624156
                    ]
                ]
            },
            {
                "area_code": "8",
                "shape_type": "polygon",
                "points": [
                    [
                        879.2770758224099,
                        1266.5119870200654
                    ],
                    [
                        723.6914388204597,
                        1331.2543621094242
                    ],
                    [
                        543.4585721944383,
                        916.5948645132928
                    ],
                    [
                        374.008868528948,
                        525.0576437347896
                    ],
                    [
                        409.43926111355046,
                        424.8611108584011
                    ],
                    [
                        625.1025203241744,
                        790.1930845769256
                    ]
                ]
            },
            {
                "area_code": "12",
                "shape_type": "polygon",
                "points": [
                    [
                        31.104286384055857,
                        1399.0797074411335
                    ],
                    [
                        49.58970860210934,
                        1400.6211925623088
                    ],
                    [
                        48.243262063531766,
                        1446.019150464965
                    ],
                    [
                        34.68728577029254,
                        1442.9361802226142
                    ]
                ]
            }
        ],
        "PM": [
            {
                "PM_code": "17",
                "shape_type": "bbox",
                "points": [
                    1273.0,
                    212.0,
                    56.0,
                    82.0
                ]
            }
        ]
    }
}