{
    "info": {
        "video_id": "S000530",
        "clip_id": "047",
        "device": "C",
        "time": "N",
        "weather": "F",
        "is_scripted": "0"
    },
    "description": {
        "frame_id": "0021",
        "imageWidth": 1920,
        "imageHeight": 1080
    },
    "annotations": {
        "environment": [
            {
                "area_code": "1",
                "shape_type": "polygon",
                "points": [
                    [
                        406.9995860913922,
                        1.542862653080904
                    ],
                    [
                        389.11606752013665,
                        100.89342861916847
                    ],
                    [
                        381.16783704402303,
                        223.28400229691974
                    ],
                    [
                        387.1290099011082,
                        302.8876274531807
                    ],
                    [
                        424.8831046626478,
                        407.36738547077323
                    ],
                    [
                        458.66308418613033,
                        479.0106481114082
                    ],
                    [
                        549.0742058519221,
                        538.7133669786039
                    ],
                    [
                        584.8412429944333,
                        421.29801987311896
                    ],
                    [
                        657.3688460889695,
                        450.1543339922636
                    ],
                    [
                        692.8940931413538,
                        348.77182134137274
                    ],
                    [
                        1075.9615447596711,
                        501.07594478487516
                    ],
                    [
                        1078.4571373469191,
                        1.542862653080904
                    ]
                ]
            },
            {
                "area_code": "1",
                "shape_type": "polygon",
                "points": [
                    [
                        198.02439425628393,
                        1136.9990548108174
                    ],
                    [
                        200.04402659037834,
                        1065.6983487538466
                    ],
                    [
                        219.23053376427544,
                        986.306782435092
                    ],
                    [
                        250.5348349427391,
                        981.2499947714771
                    ],
                    [
                        272.75079061777785,
                        1000.9714666595754
                    ],
                    [
                        298.50110287748186,
                        1067.7210638192926
                    ],
                    [
                        311.12380496557205,
                        1108.175365128212
                    ],
                    [
                        310.61889688204843,
                        1146.101272605324
                    ],
                    [
                        304.55999987976514,
                        1160.7659568298075
                    ],
                    [
                        272.75079061777785,
                        1170.3738533906758
                    ],
                    [
                        292.3515925329832,
                        1245.09333478742
                    ],
                    [
                        326.80393702005927,
                        1413.900722400621
                    ],
                    [
                        396.3078287050682,
                        1724.5744075975065
                    ],
                    [
                        450.34887251870083,
                        1918.0826628984746
                    ],
                    [
                        400.29985873942326,
                        1912.298962008215
                    ],
                    [
                        336.54202610398426,
                        1591.1095271786023
                    ],
                    [
                        276.9518959855132,
                        1302.7627001859503
                    ],
                    [
                        260.8826474142401,
                        1228.9995583971322
                    ]
                ]
            },
            {
                "area_code": "2",
                "shape_type": "polygon",
                "points": [
                    [
                        390.53575708453167,
                        360.4204395043108
                    ],
                    [
                        406.6928157572871,
                        421.1018914676902
                    ],
                    [
                        449.1050947732702,
                        506.56160298278263
                    ],
                    [
                        395.5848379197678,
                        689.1116376392822
                    ],
                    [
                        351.2670052685011,
                        886.4794891527532
                    ],
                    [
                        329.0510495934624,
                        1014.9218958085728
                    ],
                    [
                        317.94307175594304,
                        1099.3702497909424
                    ],
                    [
                        274.5209765729128,
                        983.5698122941601
                    ],
                    [
                        297.7467484149987,
                        824.2810008902894
                    ],
                    [
                        327.03141725936797,
                        658.4183655237194
                    ]
                ]
            },
            {
                "area_code": "3",
                "shape_type": "polygon",
                "points": [
                    [
                        380.6529831148585,
                        330.08393992398675
                    ],
                    [
                        389.9509131057838,
                        360.93034467203785
                    ],
                    [
                        365.25328656738844,
                        471.5117956556174
                    ],
                    [
                        337.3636706428599,
                        606.7781886679601
                    ],
                    [
                        310.88855548279645,
                        741.6784496580606
                    ],
                    [
                        293.5670226892859,
                        851.0703709572009
                    ],
                    [
                        274.23946677373715,
                        982.8790435161509
                    ],
                    [
                        261.61171560481165,
                        964.8338967385411
                    ],
                    [
                        276.7269443994629,
                        871.7610492999308
                    ],
                    [
                        296.4218783815519,
                        740.3396485485515
                    ],
                    [
                        325.7324739248641,
                        577.9321583001697
                    ]
                ]
            },
            {
                "area_code": "4",
                "shape_type": "polygon",
                "points": [
                    [
                        300.62823888605703,
                        167.8199386764623
                    ],
                    [
                        384.402588104294,
                        112.29641012997027
                    ],
                    [
                        378.85869734720484,
                        191.26320628498112
                    ],
                    [
                        379.4746852091036,
                        330.6889557461723
                    ],
                    [
                        334.5075712904911,
                        528.7228742286607
                    ],
                    [
                        304.94015391934863,
                        687.2733946336435
                    ],
                    [
                        281.1131793082628,
                        842.2788766700356
                    ],
                    [
                        261.48279689610314,
                        964.9865527007445
                    ],
                    [
                        225.64626295260703,
                        939.2486214206259
                    ],
                    [
                        206.89880628612173,
                        798.4280780056098
                    ],
                    [
                        199.53373402428824,
                        736.0646944932455
                    ],
                    [
                        215.57824734308474,
                        588.1480579841215
                    ],
                    [
                        239.89355768119535,
                        416.8693368831007
                    ]
                ]
            },
            {
                "area_code": "5",
                "shape_type": "polygon",
                "points": [
                    [
                        362.78445646403605,
                        838.6714911889014
                    ],
                    [
                        368.74014021167636,
                        815.8349263478028
                    ],
                    [
                        414.60604345161516,
                        939.5693460736652
                    ],
                    [
                        485.9786889691376,
                        1121.3631463290355
                    ],
                    [
                        617.8651489637756,
                        1447.4754510335615
                    ],
                    [
                        734.4045740637195,
                        1721.756663565827
                    ],
                    [
                        816.6961810462803,
                        1918.463994514266
                    ],
                    [
                        783.9097303323119,
                        1918.4024822017104
                    ],
                    [
                        681.0920010397031,
                        1663.7171919193356
                    ],
                    [
                        589.424915261688,
                        1438.5239418028416
                    ],
                    [
                        486.6902647821476,
                        1174.8637495970072
                    ],
                    [
                        407.0289037449646,
                        963.3407273379336
                    ]
                ]
            },
            {
                "area_code": "7",
                "shape_type": "polygon",
                "points": [
                    [
                        394.7016136105698,
                        932.1057737888208
                    ],
                    [
                        402.78014294694754,
                        950.3102093778344
                    ],
                    [
                        371.9807498520074,
                        1086.3377975290764
                    ],
                    [
                        344.210805258209,
                        1222.3653856803185
                    ],
                    [
                        340.1715405900202,
                        1198.0928048949668
                    ],
                    [
                        355.823691179252,
                        1111.1160570807897
                    ],
                    [
                        372.99056601905465,
                        1027.1733818647815
                    ]
                ]
            },
            {
                "area_code": "8",
                "shape_type": "polygon",
                "points": [
                    [
                        318.6461712338406,
                        1100.1057420454026
                    ],
                    [
                        339.3141850212346,
                        1194.2684512762958
                    ],
                    [
                        361.1979643255342,
                        1082.2472971912678
                    ],
                    [
                        395.2738820645774,
                        930.6169479044349
                    ],
                    [
                        361.8594461596896,
                        839.241748933793
                    ],
                    [
                        340.93520571044206,
                        948.7148345319412
                    ],
                    [
                        327.96704019678305,
                        1027.4543413888084
                    ]
                ]
            },
            {
                "area_code": "12",
                "shape_type": "polygon",
                "points": [
                    [
                        130.49574980778291,
                        550.7761606063565
                    ],
                    [
                        129.4332699896327,
                        569.1826603978642
                    ],
                    [
                        135.3214958351529,
                        570.0635736944582
                    ],
                    [
                        136.50163146129623,
                        551.3930887013174
                    ]
                ]
            }
        ],
        "PM": [
            {
                "PM_code": "23",
                "shape_type": "bbox",
                "points": [
                    244.91583737031016,
                    321.10465273261906,
                    77.9669509916913,
                    82.91486382060485
                ]
            }
        ]
    }
}