{
    "info": {
        "video_id": "S001464",
        "clip_id": "000",
        "device": "C",
        "time": "N",
        "weather": "F",
        "is_scripted": "0"
    },
    "description": {
        "frame_id": "0192",
        "imageWidth": 1920,
        "imageHeight": 1080
    },
    "annotations": {
        "environment": [
            {
                "area_code": "1",
                "shape_type": "polygon",
                "points": [
                    [
                        489.3074248670661,
                        801.8144812153596
                    ],
                    [
                        641.3985080379192,
                        447.14815753051596
                    ],
                    [
                        512.4098678803604,
                        275.5975987916512
                    ],
                    [
                        383.42122772280123,
                        262.1048582166843
                    ],
                    [
                        354.5431739561836,
                        156.09046798480168
                    ],
                    [
                        416.14968865830133,
                        163.8006054562113
                    ],
                    [
                        479.6814069448603,
                        3.8152529244610975
                    ],
                    [
                        1070.7189073683023,
                        1.5428750512282732
                    ],
                    [
                        1076.494518121626,
                        1175.7561485787278
                    ],
                    [
                        910.9270098596844,
                        1139.1329955895317
                    ],
                    [
                        733.8082800910959,
                        1062.0316208754355
                    ],
                    [
                        625.9968793623899,
                        984.9302461613389
                    ],
                    [
                        537.4375144780956,
                        902.0462683436851
                    ]
                ]
            },
            {
                "area_code": "2",
                "shape_type": "polygon",
                "points": [
                    [
                        548.9887359847427,
                        1148.7706674287938
                    ],
                    [
                        618.296065024625,
                        1063.9591552432878
                    ],
                    [
                        699.1546155711546,
                        1121.78518627886
                    ],
                    [
                        845.4700879886842,
                        1208.5242328322188
                    ],
                    [
                        1041.8408536016848,
                        1324.1762949033637
                    ],
                    [
                        1070.7189073683023,
                        1331.8864323747732
                    ],
                    [
                        1078.4571249487717,
                        1775.2193369808278
                    ],
                    [
                        897.4505847685961,
                        1748.233855830894
                    ],
                    [
                        641.3985080379192,
                        1678.8426185882074
                    ],
                    [
                        441.17114512570964,
                        1615.029183268485
                    ],
                    [
                        364.1630017480625,
                        1586.7586792066493
                    ],
                    [
                        339.34926665970954,
                        1405.9987895991567
                    ],
                    [
                        430.9033926753567,
                        1294.6301372343505
                    ]
                ]
            },
            {
                "area_code": "10",
                "shape_type": "polygon",
                "points": [
                    [
                        251.5052287192808,
                        1544.0315185114944
                    ],
                    [
                        274.60767173257494,
                        1540.6904589405501
                    ],
                    [
                        275.89114078886905,
                        1551.9986605652844
                    ],
                    [
                        251.24853490802198,
                        1554.5687063890875
                    ]
                ]
            }
        ],
        "PM": [
            {
                "PM_code": "14",
                "shape_type": "bbox",
                "points": [
                    610.3362199542554,
                    609.0,
                    185.0,
                    247.0
                ]
            }
        ]
    }
}